dulogpy/__init__.py
dulogpy/dulogpy.py
dulogpy-0.0.1.dist-info/METADATA
dulogpy-0.0.1.dist-info/WHEEL
dulogpy-0.0.1.dist-info/RECORD
