Metadata-Version: 2.1
Name: dulogpy
Version: 0.0.1
Summary: Functions to handle data retrieved by the dulopg biologging system
Home-page: https://github.com/jhdezmontero/dulogpy
License: MIT
Keywords: dulog,range data,proximity data
Author: Jesús R. Hernández Montero
Author-email: jesus.hdezmontero@gmail.com
Requires-Python: >=3.9,<4.0
Classifier: License :: OSI Approved :: MIT License
Classifier: Operating System :: OS Independent
Classifier: Programming Language :: Python :: 3
Classifier: Programming Language :: Python :: 3.9
Classifier: Programming Language :: Python :: 3.10
Classifier: Programming Language :: Python :: 3.11
Classifier: Programming Language :: Python :: 3
Requires-Dist: pandas (>=1.4.1,<2.0.0)
Project-URL: Repository, https://github.com/jhdezmontero/dulogpy
